ofxstatement_betterment-0.3.0-py3.4-nspkg.pth
ofxstatement/plugins/betterment.py
ofxstatement_betterment-0.3.0.dist-info/RECORD
ofxstatement_betterment-0.3.0.dist-info/DESCRIPTION.rst
ofxstatement_betterment-0.3.0.dist-info/zip-safe
ofxstatement_betterment-0.3.0.dist-info/METADATA
ofxstatement_betterment-0.3.0.dist-info/WHEEL
ofxstatement_betterment-0.3.0.dist-info/entry_points.txt
ofxstatement_betterment-0.3.0.dist-info/metadata.json
ofxstatement_betterment-0.3.0.dist-info/namespace_packages.txt
ofxstatement_betterment-0.3.0.dist-info/top_level.txt
