Metadata-Version: 2.0
Name: ofxstatement-betterment
Version: 0.3.0
Summary: Betterment plugin for ofxstatement
Home-page: https://github.com/cmayes/ofxstatement-betterment
Author: Chris Mayes
Author-email: cmayes@cmay.es
License: GPLv3
Keywords: ofx,banking,statement
Platform: UNKNOWN
Classifier: Development Status :: 4 - Beta
Classifier: Programming Language :: Python :: 3
Classifier: Natural Language :: English
Classifier: Topic :: Office/Business :: Financial :: Accounting
Classifier: Topic :: Utilities
Classifier: Environment :: Console
Classifier: Operating System :: OS Independent
Classifier: License :: OSI Approved :: GNU Affero General Public License v3
Requires-Dist: ofxstatement
